{
    "type":  "FeatureCollection",
    "features":  [
                     {
                         "type":  "Feature",
                         "id":  "critical-minerals-0",
                         "geometry":  {
                                          "type":  "Point",
                                          "coordinates":  [
                                                              -77.04,
                                                              38.9
                                                          ]
                                      },
                         "properties":  {
                                            "name":  "critical-minerals site 0",
                                            "ts":  1772435598916
                                        }
                     },
                     {
                         "type":  "Feature",
                         "id":  "critical-minerals-1",
                         "geometry":  {
                                          "type":  "Point",
                                          "coordinates":  [
                                                              2.35,
                                                              48.86
                                                          ]
                                      },
                         "properties":  {
                                            "name":  "critical-minerals site 1",
                                            "ts":  1772435598916
                                        }
                     },
                     {
                         "type":  "Feature",
                         "id":  "critical-minerals-2",
                         "geometry":  {
                                          "type":  "Point",
                                          "coordinates":  [
                                                              139.76,
                                                              35.68
                                                          ]
                                      },
                         "properties":  {
                                            "name":  "critical-minerals site 2",
                                            "ts":  1772435598916
                                        }
                     },
                     {
                         "type":  "Feature",
                         "id":  "critical-minerals-3",
                         "geometry":  {
                                          "type":  "Point",
                                          "coordinates":  [
                                                              55.27,
                                                              25.2
                                                          ]
                                      },
                         "properties":  {
                                            "name":  "critical-minerals site 3",
                                            "ts":  1772435598916
                                        }
                     },
                     {
                         "type":  "Feature",
                         "id":  "critical-minerals-4",
                         "geometry":  {
                                          "type":  "Point",
                                          "coordinates":  [
                                                              -46.63,
                                                              -23.55
                                                          ]
                                      },
                         "properties":  {
                                            "name":  "critical-minerals site 4",
                                            "ts":  1772435598917
                                        }
                     }
                 ]
}
